appdog/__init__.py
appdog/__main__.py
appdog/py.typed
appdog/_internal/__init__.py
appdog/_internal/case.py
appdog/_internal/cli.py
appdog/_internal/clients.py
appdog/_internal/errors.py
appdog/_internal/generator.py
appdog/_internal/logging.py
appdog/_internal/managers.py
appdog/_internal/mcp.py
appdog/_internal/project.py
appdog/_internal/registry.py
appdog/_internal/schema.py
appdog/_internal/settings.py
appdog/_internal/specs.py
appdog/_internal/store.py
appdog/_internal/typing.py
appdog/_internal/utils.py
appdog/_internal/templates/__init__.j2
appdog/_internal/templates/client.j2
appdog/_internal/templates/models.j2
appdog/_internal/templates/models_error.j2
appdog/_internal/templates/server.j2
appdog-0.1.0.dist-info/METADATA
appdog-0.1.0.dist-info/WHEEL
appdog-0.1.0.dist-info/entry_points.txt
appdog-0.1.0.dist-info/licenses/LICENSE
appdog-0.1.0.dist-info/RECORD
