Metadata-Version: 2.4
Name: appdog
Version: 0.1.0
Summary: Generate async API clients and MCP servers from OpenAPI specifications
Project-URL: Homepage, https://github.com/rodolphebarbanneau/appdog
Project-URL: Documentation, https://github.com/rodolphebarbanneau/appdog#readme
Project-URL: Issues, https://github.com/rodolphebarbanneau/appdog/issues
Project-URL: Source, https://github.com/rodolphebarbanneau/appdog
Author: Rodolphe Barbanneau
License: MIT License
License-File: LICENSE
Keywords: api,client,mcp,openapi,server
Classifier: Development Status :: 5 - Production/Stable
Classifier: License :: OSI Approved :: MIT License
Classifier: Operating System :: OS Independent
Classifier: Programming Language :: Python
Classifier: Programming Language :: Python :: 3
Classifier: Programming Language :: Python :: 3 :: Only
Classifier: Programming Language :: Python :: 3.10
Classifier: Programming Language :: Python :: 3.11
Classifier: Programming Language :: Python :: 3.12
Classifier: Programming Language :: Python :: 3.13
Classifier: Programming Language :: Python :: Implementation :: CPython
Classifier: Programming Language :: Python :: Implementation :: PyPy
Classifier: Topic :: Internet
Classifier: Topic :: Internet :: WWW/HTTP
Classifier: Topic :: Internet :: WWW/HTTP :: HTTP Servers
Classifier: Topic :: Software Development
Classifier: Topic :: Software Development :: Libraries
Classifier: Topic :: Software Development :: Libraries :: Application Frameworks
Classifier: Topic :: Software Development :: Libraries :: Python Modules
Classifier: Typing :: Typed
Requires-Python: >=3.10
Requires-Dist: datamodel-code-generator>=0.25.2
Requires-Dist: httpx>=0.26.0
Requires-Dist: jinja2>=3.1.3
Requires-Dist: mcp>=1.6.0
Requires-Dist: pydantic-core>=2.33.1
Requires-Dist: pydantic-settings>=2.8.1
Requires-Dist: pydantic>=2.0.0
Requires-Dist: pyyaml>=6.0.1
Requires-Dist: rich>=13.7.0
Requires-Dist: typer>=0.9.0
Provides-Extra: dev
Requires-Dist: mypy>=1.0.0; extra == 'dev'
Requires-Dist: ruff>=0.1.0; extra == 'dev'
Requires-Dist: types-pyyaml>=6.0.0; extra == 'dev'
Requires-Dist: types-requests>=2.31.0; extra == 'dev'
Provides-Extra: test
Requires-Dist: pytest-asyncio>=0.21.0; extra == 'test'
Requires-Dist: pytest-cov>=6.1.1; extra == 'test'
Requires-Dist: pytest-mock>=3.14.0; extra == 'test'
Requires-Dist: pytest>=7.0.0; extra == 'test'
